qwop_gym/__init__.py
qwop_gym/envs/v1/qwop_env.py
qwop_gym/envs/v1/game/QWOP.html
qwop_gym/envs/v1/game/extensions.js
qwop_gym/envs/v1/game/seedrandom.js
qwop_gym/envs/v1/game/ws.js
qwop_gym/envs/v1/game/assets/assetbundle.parcel
qwop_gym/envs/v1/game/assets/howler.js
qwop_gym/envs/v1/util/log.py
qwop_gym/envs/v1/util/wsclient.py
qwop_gym/envs/v1/util/wsproto.py
qwop_gym/envs/v1/util/wsserver.py
qwop_gym/tools/benchmark.py
qwop_gym/tools/bootstrap.py
qwop_gym/tools/common.py
qwop_gym/tools/main.py
qwop_gym/tools/patch.py
qwop_gym/tools/perftest.py
qwop_gym/tools/play.py
qwop_gym/tools/replay.py
qwop_gym/tools/spectate.py
qwop_gym/tools/train_adversarial.py
qwop_gym/tools/train_bc.py
qwop_gym/tools/train_sb3.py
qwop_gym/tools/templates/benchmark.yml
qwop_gym/tools/templates/env.yml
qwop_gym/tools/templates/play.yml
qwop_gym/tools/templates/record.yml
qwop_gym/tools/templates/replay.yml
qwop_gym/tools/templates/spectate.yml
qwop_gym/tools/templates/spectate_record.yml
qwop_gym/tools/templates/train_airl.yml
qwop_gym/tools/templates/train_bc.yml
qwop_gym/tools/templates/train_dqn.yml
qwop_gym/tools/templates/train_gail.yml
qwop_gym/tools/templates/train_ppo.yml
qwop_gym/tools/templates/train_qrdqn.yml
qwop_gym/tools/templates/wandb/dqn.yml
qwop_gym/tools/templates/wandb/gail.yml
qwop_gym/tools/templates/wandb/ppo.yml
qwop_gym/tools/templates/wandb/qrdqn.yml
qwop_gym/wrappers/absorb_wrapper.py
qwop_gym/wrappers/record_wrapper.py
qwop_gym/wrappers/verbose_wrapper.py
qwop_gym-1.0.1.dist-info/LICENSE
qwop_gym-1.0.1.dist-info/METADATA
qwop_gym-1.0.1.dist-info/WHEEL
qwop_gym-1.0.1.dist-info/entry_points.txt
qwop_gym-1.0.1.dist-info/top_level.txt
qwop_gym-1.0.1.dist-info/RECORD
