Metadata-Version: 2.1
Name: qwop-gym
Version: 1.0.1
Summary: A Gymnasium environment for Benett Foddy's game QWOP
Author-email: Simeon Manolov <s.manolloff@gmail.com>
License: Apache License v2.0
Project-URL: Homepage, https://github.com/smanolloff/qwop-gym
Project-URL: Bug Tracker, https://github.com/smanolloff/qwop-gym/issues
Keywords: gym,gymnasium,Reinforcement Learning,AI,game,QWOP,Farama-Foundation
Classifier: Programming Language :: Python :: 3
Classifier: Programming Language :: JavaScript
Classifier: License :: OSI Approved :: Apache Software License
Classifier: Operating System :: OS Independent
Classifier: Topic :: Education
Classifier: Topic :: Games/Entertainment
Classifier: Topic :: Scientific/Engineering :: Artificial Intelligence
Requires-Python: >=3.10
License-File: LICENSE
Requires-Dist: gymnasium ~=0.29.1
Requires-Dist: websockets ~=11.0
Requires-Dist: numpy ~=1.24
Requires-Dist: selenium ~=4.11
Requires-Dist: pillow ~=10.0
Requires-Dist: pygame ~=2.5
Requires-Dist: pyyaml >=6.0
Provides-Extra: sb3
Requires-Dist: stable-baselines3 ~=2.1 ; extra == 'sb3'
Requires-Dist: sb3-contrib ~=2.1 ; extra == 'sb3'
Requires-Dist: tensorboard ; extra == 'sb3'
Requires-Dist: tensorflow ; extra == 'sb3'
Requires-Dist: tqdm ; extra == 'sb3'
Requires-Dist: rich ; extra == 'sb3'
